RobustPreprocessor/RobustPreprocessor.py
RobustPreprocessor/__init__.py
robustpreprocessor-1.0.0.dist-info/LICENSE
robustpreprocessor-1.0.0.dist-info/METADATA
robustpreprocessor-1.0.0.dist-info/WHEEL
robustpreprocessor-1.0.0.dist-info/top_level.txt
robustpreprocessor-1.0.0.dist-info/RECORD
