Metadata-Version: 2.1
Name: robustpreprocessor
Version: 1.0.0
Summary: RobustPreprocessor is designed to preprocess datasets effectively to ensure robust data preparation before further analysis or modeling.
Home-page: https://github.com/nqmn/robustpreprocessor
Author: Mohd Adil
Author-email: mohdadil@live.com
Keywords: data preprocessing,outlier handling,missing data,data cleaning,feature engineering,robust preprocessing
Classifier: Programming Language :: Python :: 3
Classifier: License :: OSI Approved :: MIT License
Classifier: Operating System :: OS Independent
Classifier: Topic :: Scientific/Engineering
Classifier: Topic :: Scientific/Engineering :: Artificial Intelligence
Classifier: Topic :: Software Development :: Libraries :: Python Modules
Requires-Python: >=3.8
License-File: LICENSE
Requires-Dist: numpy>=1.20.0
Requires-Dist: pandas>=1.3.0
Requires-Dist: scikit-learn>=1.0.0
Requires-Dist: scipy>=1.7.0
Requires-Dist: matplotlib>=3.2.0
